Metadata-Version: 2.1
Name: list-slice
Version: 1.0.0
Summary: This library has a function to split the data list into several small sections
Home-page: https://github.com/yusriltakeuchi/list-slicer
Author: Yusril Rapsanjani
Author-email: yuranicorp@gmail.com
License: MIT
Platform: UNKNOWN
Classifier: License :: OSI Approved :: MIT License
Classifier: Programming Language :: Python :: 3
Classifier: Programming Language :: Python :: 3.7
